cluefin_openapi/__init__.py
cluefin_openapi/_rate_limiter.py
cluefin_openapi/dart/__init__.py
cluefin_openapi/dart/_client.py
cluefin_openapi/dart/_exceptions.py
cluefin_openapi/dart/_major_shareholder_disclosure.py
cluefin_openapi/dart/_major_shareholder_disclosure_types.py
cluefin_openapi/dart/_model.py
cluefin_openapi/dart/_periodic_report_financial_statement.py
cluefin_openapi/dart/_periodic_report_financial_statement_types.py
cluefin_openapi/dart/_periodic_report_key_information.py
cluefin_openapi/dart/_periodic_report_key_information_types.py
cluefin_openapi/dart/_public_disclosure.py
cluefin_openapi/dart/_public_disclosure_types.py
cluefin_openapi/dart/_share_disclosure_comprehensive.py
cluefin_openapi/dart/_share_disclosure_comprehensive_types.py
cluefin_openapi/kis/__init__.py
cluefin_openapi/kis/_auth.py
cluefin_openapi/kis/_auth_types.py
cluefin_openapi/kis/_client.py
cluefin_openapi/kis/_domestic_account.py
cluefin_openapi/kis/_domestic_account_types.py
cluefin_openapi/kis/_domestic_basic_quote.py
cluefin_openapi/kis/_domestic_basic_quote_types.py
cluefin_openapi/kis/_domestic_issue_other.py
cluefin_openapi/kis/_domestic_issue_other_types.py
cluefin_openapi/kis/_domestic_market_analysis.py
cluefin_openapi/kis/_domestic_market_analysis_types.py
cluefin_openapi/kis/_domestic_ranking_analysis.py
cluefin_openapi/kis/_domestic_ranking_analysis_types.py
cluefin_openapi/kis/_domestic_realtime_quote.py
cluefin_openapi/kis/_domestic_realtime_quote_types.py
cluefin_openapi/kis/_domestic_stock_info.py
cluefin_openapi/kis/_domestic_stock_info_types.py
cluefin_openapi/kis/_exceptions.py
cluefin_openapi/kis/_model.py
cluefin_openapi/kis/_onmarket_bond_accout.py
cluefin_openapi/kis/_onmarket_bond_basic_quote.py
cluefin_openapi/kis/_onmarket_bond_realtime_quote.py
cluefin_openapi/kis/_overseas_account.py
cluefin_openapi/kis/_overseas_account_types.py
cluefin_openapi/kis/_overseas_basic_quote.py
cluefin_openapi/kis/_overseas_basic_quote_types.py
cluefin_openapi-0.3.5.dist-info/METADATA
cluefin_openapi-0.3.5.dist-info/WHEEL
cluefin_openapi-0.3.5.dist-info/RECORD
