Metadata-Version: 2.4
Name: cluefin-openapi
Version: 0.3.5
Summary: OpenAPI Client for Cluefin
Author-email: Hangoo Kang <kgcrom@hotmail.com>
Requires-Python: >=3.10
Requires-Dist: defusedxml>=0.7.1
Requires-Dist: loguru>=0.7.3
Requires-Dist: pydantic<3.0.0,>=2.12.0
Requires-Dist: requests>=2.32.4
